Metadata-Version: 2.1
Name: tencirchem-ng
Version: 2024.10
Summary: Efficient quantum computational chemistry based on TensorCircuit
Home-page: https://github.com/tensorcircuit/TenCirChem-NG
Author: TenCirChem-NG Authors
Author-email: liw31@g163.com
Classifier: Programming Language :: Python :: 3
Classifier: Operating System :: OS Independent
Requires-Python: >=3.9
License-File: LICENSE
Requires-Dist: numpy
Requires-Dist: scipy
Requires-Dist: pandas
Requires-Dist: tensorcircuit-ng[qiskit]
Requires-Dist: pyscf
Requires-Dist: openfermion
Requires-Dist: pylatexenc
Requires-Dist: noisyopt
Requires-Dist: renormalizer
Provides-Extra: jax
Requires-Dist: jax ; extra == 'jax'
Requires-Dist: jaxlib ; extra == 'jax'
